BPt/__init__.py
BPt/p.py
BPt/shared_docs.py
BPt/util.py
BPt/dataset/__init__.py
BPt/dataset/_data_files.py
BPt/dataset/_encoding.py
BPt/dataset/_filtering.py
BPt/dataset/_plotting.py
BPt/dataset/_subjects.py
BPt/dataset/_validation.py
BPt/dataset/data_file.py
BPt/dataset/dataset.py
BPt/dataset/fake_dataset.py
BPt/dataset/funcs.py
BPt/dataset/helpers.py
BPt/dataset/tests/__init__.py
BPt/dataset/tests/datasets.py
BPt/dataset/tests/test_data_file.py
BPt/dataset/tests/test_data_files.py
BPt/dataset/tests/test_dataset.py
BPt/dataset/tests/test_encoding.py
BPt/dataset/tests/test_filtering.py
BPt/dataset/tests/test_funcs.py
BPt/dataset/tests/test_helpers.py
BPt/dataset/tests/test_plotting.py
BPt/dataset/tests/test_subjects.py
BPt/dataset/tests/test_validation.py
BPt/datasets/__init__.py
BPt/datasets/from_sklearn.py
BPt/datasets/tests/__init__.py
BPt/datasets/tests/test_from_sklearn.py
BPt/default/__init__.py
BPt/default/helpers.py
BPt/default/pipelines.py
BPt/default/options/__init__.py
BPt/default/options/all_keys.py
BPt/default/options/ensembles.py
BPt/default/options/feature_selectors.py
BPt/default/options/imputers.py
BPt/default/options/loaders.py
BPt/default/options/models.py
BPt/default/options/samplers.py
BPt/default/options/scalers.py
BPt/default/options/scorers.py
BPt/default/options/transformers.py
BPt/default/params/Params.py
BPt/default/params/__init__.py
BPt/default/params/default_params.py
BPt/default/params/ensemble_params.py
BPt/default/params/feat_selector_params.py
BPt/default/params/imputer_params.py
BPt/default/params/model_params.py
BPt/default/params/scaler_params.py
BPt/default/params/transformer_params.py
BPt/default/tests/__init__.py
BPt/default/tests/test_Params.py
BPt/extensions/BPtLGBM.py
BPt/extensions/__init__.py
BPt/extensions/feat_selectors.py
BPt/extensions/loaders.py
BPt/extensions/residualizer.py
BPt/extensions/samplers.py
BPt/extensions/scalers.py
BPt/extensions/mv_transformer/__init__.py
BPt/extensions/mv_transformer/constructor.py
brain_pred_toolbox-2.3.2.dist-info/LICENSE
brain_pred_toolbox-2.3.2.dist-info/METADATA
brain_pred_toolbox-2.3.2.dist-info/WHEEL
brain_pred_toolbox-2.3.2.dist-info/top_level.txt
brain_pred_toolbox-2.3.2.dist-info/RECORD
