Metadata-Version: 2.1
Name: brain-pred-toolbox
Version: 2.3.2
Summary: The Brain Predictability toolbox (BPt) is a Python based machine learning library designed to work with a range of neuroimaging data. Warning: Not actively maintained as of 11/30/22.
Home-page: http://github.com/sahahn/BPt
Author: Sage Hahn
Author-email: sahahn@euvm.edu
License: MIT
Requires-Python: >=3.8
License-File: LICENSE
Requires-Dist: scikit-learn (<1.1.4,>=1.1.0)
Requires-Dist: numpy (<1.24,>=1.21)
Requires-Dist: scipy (<2.0,>=1.2)
Requires-Dist: pandas (<1.6,>=1.1.5)
Requires-Dist: matplotlib (<3.7,>=3.2.2)
Requires-Dist: seaborn (<0.13,>=0.9)
Requires-Dist: scikit-image (>=0.16)
Requires-Dist: tqdm (>=4.51)
Requires-Dist: nevergrad (<0.6,>=0.5.0)
Requires-Dist: Ipython
Requires-Dist: joblib (<2,>=1)
Requires-Dist: loky
Requires-Dist: threadpoolctl (>=3)
Provides-Extra: extra
Requires-Dist: lightgbm (>=3.3.0) ; extra == 'extra'
Requires-Dist: nilearn (>=0.9) ; extra == 'extra'
Requires-Dist: python-docx ; extra == 'extra'
Requires-Dist: mvlearn ; extra == 'extra'
Requires-Dist: imblearn ; extra == 'extra'
Requires-Dist: xgboost (>=1.4) ; extra == 'extra'
Requires-Dist: bp-neurotools ; extra == 'extra'
